MANIFEST.in
README.rst
pyproject.toml
setup.py
tutor_cairn.egg-info/PKG-INFO
tutor_cairn.egg-info/SOURCES.txt
tutor_cairn.egg-info/dependency_links.txt
tutor_cairn.egg-info/entry_points.txt
tutor_cairn.egg-info/requires.txt
tutor_cairn.egg-info/top_level.txt
tutorcairn/__about__.py
tutorcairn/__init__.py
tutorcairn/plugin.py
tutorcairn/patches/.gitignore
tutorcairn/patches/caddyfile
tutorcairn/patches/k8s-deployments
tutorcairn/patches/k8s-jobs
tutorcairn/patches/k8s-services
tutorcairn/patches/k8s-volumes
tutorcairn/patches/kustomization-configmapgenerator
tutorcairn/patches/local-docker-compose-dev-services
tutorcairn/patches/local-docker-compose-jobs-services
tutorcairn/patches/local-docker-compose-permissions-command
tutorcairn/patches/local-docker-compose-permissions-volumes
tutorcairn/patches/local-docker-compose-services
tutorcairn/templates/cairn/apps/.gitignore
tutorcairn/templates/cairn/apps/clickhouse/auth.json
tutorcairn/templates/cairn/apps/clickhouse/migrations.d/0001_create.sql
tutorcairn/templates/cairn/apps/clickhouse/migrations.d/0002_grades.sql
tutorcairn/templates/cairn/apps/clickhouse/migrations.d/0003_course_enrollments.sql
tutorcairn/templates/cairn/apps/clickhouse/migrations.d/0004_video_views.sql
tutorcairn/templates/cairn/apps/clickhouse/migrations.d/0005_course_blocks.sql
tutorcairn/templates/cairn/apps/clickhouse/migrations.d/0006_course_block_completion.sql
tutorcairn/templates/cairn/apps/clickhouse/migrations.d/0007_fix_video_segments.sql
tutorcairn/templates/cairn/apps/clickhouse/migrations.d/0008_rename_openedx_tables.sql
tutorcairn/templates/cairn/apps/clickhouse/migrations.d/0009_add_graded_column_to_course_blocks.sql
tutorcairn/templates/cairn/apps/clickhouse/migrations.d/0010_modify_graded_bool.sql
tutorcairn/templates/cairn/apps/clickhouse/migrations.d/0011_modify_events_type.sql
tutorcairn/templates/cairn/apps/clickhouse/migrations.d/0012_modify_course_enrollments.sql
tutorcairn/templates/cairn/apps/clickhouse/migrations.d/0013_modify_course_block_completion.sql
tutorcairn/templates/cairn/apps/clickhouse/users.d/cairn.xml
tutorcairn/templates/cairn/apps/openedx/scripts/importcoursedata.py
