Metadata-Version: 2.1
Name: tutor-cairn
Version: 19.0.0
Summary: Scalable, real-time analytics for Open edX
Home-page: https://github.com/overhangio/tutor-cairn
Author: Edly
Author-email: hello@edly.io
Maintainer: Edly
Maintainer-email: danyal.faheem@arbisoft.com
License: AGPLv3
Project-URL: Code, https://github.com/overhangio/tutor-cairn
Project-URL: Issue tracker, https://github.com/overhangio/tutor-cairn/issues
Classifier: Development Status :: 5 - Production/Stable
Classifier: Intended Audience :: Developers
Classifier: License :: OSI Approved :: GNU Affero General Public License v3
Classifier: Operating System :: OS Independent
Classifier: Programming Language :: Python
Classifier: Programming Language :: Python :: 3.9
Classifier: Programming Language :: Python :: 3.10
Classifier: Programming Language :: Python :: 3.11
Classifier: Programming Language :: Python :: 3.12
Requires-Python: >=3.9
Requires-Dist: tutor<20.0.0,>=19.0.0
Provides-Extra: dev
Requires-Dist: tutor[dev]<20.0.0,>=19.0.0; extra == "dev"
